tuplechanger/LICENSE
tuplechanger/README.md
tuplechanger/__init__.py
tuplechanger/requirements.txt
tuplechanger/thirdparty.json
tuplechanger-0.10.dist-info/LICENSE.rst
tuplechanger-0.10.dist-info/METADATA
tuplechanger-0.10.dist-info/WHEEL
tuplechanger-0.10.dist-info/top_level.txt
tuplechanger-0.10.dist-info/RECORD
