Metadata-Version: 2.1
Name: tuplechanger
Version: 0.10
Summary: Changes values in tuples using ctypes 
Home-page: https://github.com/hansalemaos/tuplechanger
Author: Johannes Fischer
Author-email: aulasparticularesdealemaosp@gmail.com
License: MIT
Keywords: ctypes,hacking,tuples
Classifier: Development Status :: 4 - Beta
Classifier: Programming Language :: Python :: 3 :: Only
Classifier: Programming Language :: Python :: 3.10
Classifier: Topic :: Software Development :: Libraries :: Python Modules
Classifier: Topic :: Utilities
License-File: LICENSE.rst
